sl_shortner/__init__.py
sl_shortner/__main__.py
sl_shortner-1.2.1.dist-info/LICENSE
sl_shortner-1.2.1.dist-info/METADATA
sl_shortner-1.2.1.dist-info/WHEEL
sl_shortner-1.2.1.dist-info/entry_points.txt
sl_shortner-1.2.1.dist-info/top_level.txt
sl_shortner-1.2.1.dist-info/RECORD
